README.md
setup.cfg
setup.py
dataneuronalp/__init__.py
dataneuronalp/config.py
dataneuronalp/config_variables.py
dataneuronalp/mlc_prediction.py
dataneuronalp/ner_prediction.py
dataneuronalp/prediction.py
dataneuronalp.egg-info/PKG-INFO
dataneuronalp.egg-info/SOURCES.txt
dataneuronalp.egg-info/dependency_links.txt
dataneuronalp.egg-info/requires.txt
dataneuronalp.egg-info/top_level.txt