Metadata-Version: 2.1
Name: dataneuronalp
Version: 1.0.9
Summary: dataneuronalp package
Home-page: http://20.212.37.37
Author: Nishant Chhetri
Author-email: nishant.chhetri@precily.com
License: UNKNOWN
Platform: UNKNOWN
Classifier: Programming Language :: Python :: 3
Classifier: License :: OSI Approved :: MIT License
Classifier: Operating System :: OS Independent
Requires-Python: >=3.6
